{"v":"5.8.1","fr":60,"ip":0,"op":20,"w":240,"h":240,"ddd":0,"assets":[],"layers":[{"ddd":0,"ind":1,"ty":4,"sr":1,"ks":{"o":{"a":0,"k":100},"r":{"a":1,"k":[{"i":{"x":[0.4],"y":[1]},"o":{"x":[0.6],"y":[0]},"t":0,"s":[0]},{"t":19,"s":[-90]}]},"p":{"a":0,"k":[120,120,0]},"a":{"a":0,"k":[12,12,0]},"s":{"a":0,"k":[1000,1000,100]}},"ao":0,"shapes":[{"ty":"gr","it":[{"ind":0,"ty":"sh","ks":{"a":1,"k":[{"i":{"x":0.4,"y":1},"o":{"x":0.6,"y":0},"t":0,"s":[{"i":[[0,0],[0,0],[0.051,-0.056],[0,0]],"o":[[0,0],[0.051,0.056],[0,0],[0,0]],"v":[[-1.647,-3.666],[1.597,-0.098],[1.597,0.098],[-1.647,3.666]]}]},{"t":19,"s":[{"i":[[0,0],[0,0],[0,0],[0,0]],"o":[[0,0],[0,0],[0,0],[0,0]],"v":[[0.356,-6.097],[6.356,-0.107],[6.356,-0.097],[0.356,5.903]]}]}]},"hd":false},{"ty":"st","c":{"a":0,"k":[0.270588235294,0.639215686275,0.960784373564,1]},"o":{"a":0,"k":100},"w":{"a":1,"k":[{"i":{"x":[0.4],"y":[1]},"o":{"x":[0.6],"y":[0]},"t":0,"s":[1.567]},{"t":19,"s":[1.67]}]},"lc":2,"lj":2,"bm":0,"hd":false},{"ty":"tr","p":{"a":0,"k":[8.644,12.097]},"a":{"a":0,"k":[0,0]},"s":{"a":0,"k":[100,100]},"r":{"a":0,"k":0},"o":{"a":0,"k":100}}],"bm":0,"hd":false},{"ty":"gr","it":[{"ind":0,"ty":"sh","ks":{"a":1,"k":[{"i":{"x":0.4,"y":1},"o":{"x":0.6,"y":0},"t":0,"s":[{"i":[[0,0],[0,0]],"o":[[0,0],[0,0]],"v":[[3.33,12.097],[9.33,12.097]]}]},{"t":19,"s":[{"i":[[0,0],[0,0]],"o":[[0,0],[0,0]],"v":[[9.33,12.097],[15.33,12.097]]}]}]},"hd":false},{"ty":"tm","s":{"a":1,"k":[{"i":{"x":[0.4],"y":[1]},"o":{"x":[0.6],"y":[0]},"t":0,"s":[0]},{"t":10,"s":[100]}]},"e":{"a":0,"k":100},"o":{"a":0,"k":0},"m":1,"hd":false},{"ty":"st","c":{"a":0,"k":[0.270588235294,0.639215686275,0.960784373564,1]},"o":{"a":0,"k":100},"w":{"a":0,"k":1.567},"lc":2,"lj":1,"ml":10,"bm":0,"hd":false},{"ty":"tr","p":{"a":0,"k":[0,0]},"a":{"a":0,"k":[0,0]},"s":{"a":0,"k":[100,100]},"r":{"a":0,"k":0},"o":{"a":0,"k":100}}],"bm":0,"hd":false},{"ty":"gr","it":[{"ind":0,"ty":"sh","ks":{"a":0,"k":{"i":[[0,0],[0,0]],"o":[[0,0],[0,0]],"v":[[14.663,13.43],[18.996,13.43]]}},"hd":false},{"ty":"tm","s":{"a":1,"k":[{"i":{"x":[0.833],"y":[0.833]},"o":{"x":[0.6],"y":[0]},"t":0,"s":[0]},{"t":12,"s":[100]}]},"e":{"a":0,"k":100},"o":{"a":0,"k":0},"m":1,"hd":false},{"ty":"st","c":{"a":0,"k":[0.270588235294,0.639215686275,0.960784373564,1]},"o":{"a":0,"k":100},"w":{"a":0,"k":1.567},"lc":2,"lj":1,"ml":10,"bm":0,"hd":false},{"ty":"tr","p":{"a":0,"k":[0,0]},"a":{"a":0,"k":[0,0]},"s":{"a":0,"k":[100,100]},"r":{"a":0,"k":0},"o":{"a":0,"k":100}}],"bm":0,"hd":false},{"ty":"gr","it":[{"ind":0,"ty":"sh","ks":{"a":0,"k":{"i":[[0,0],[0,0],[-0.264,-0.532],[0,0]],"o":[[0,0],[0.19,-0.497],[0,0],[0,0]],"v":[[-3.333,4.012],[-0.566,-3.482],[0.558,-3.48],[3.333,4.012]]}},"hd":false},{"ty":"tm","s":{"a":1,"k":[{"i":{"x":[0.4],"y":[1]},"o":{"x":[0.6],"y":[0]},"t":0,"s":[0]},{"t":16,"s":[100]}]},"e":{"a":0,"k":100},"o":{"a":0,"k":0},"m":1,"hd":false},{"ty":"st","c":{"a":0,"k":[0.270588235294,0.639215686275,0.960784373564,1]},"o":{"a":0,"k":100},"w":{"a":1,"k":[{"i":{"x":[0.833],"y":[0.833]},"o":{"x":[0.167],"y":[0.167]},"t":10,"s":[1.567]},{"t":14,"s":[0]}]},"lc":2,"lj":1,"ml":10,"bm":0,"hd":false},{"ty":"tr","p":{"a":0,"k":[16.662,11.752]},"a":{"a":0,"k":[0,0]},"s":{"a":0,"k":[100,100]},"r":{"a":0,"k":0},"o":{"a":0,"k":100}}],"bm":0,"hd":false}],"ip":0,"op":20,"st":0,"bm":0}]}